odoo/addons/ssi_source_document_mixin/README.rst
odoo/addons/ssi_source_document_mixin/__init__.py
odoo/addons/ssi_source_document_mixin/__manifest__.py
odoo/addons/ssi_source_document_mixin/models/__init__.py
odoo/addons/ssi_source_document_mixin/models/mixin_source_document.py
odoo/addons/ssi_source_document_mixin/static/description/icon.png
odoo14_addon_ssi_source_document_mixin-14.0.1.1.0.dist-info/METADATA
odoo14_addon_ssi_source_document_mixin-14.0.1.1.0.dist-info/WHEEL
odoo14_addon_ssi_source_document_mixin-14.0.1.1.0.dist-info/top_level.txt
odoo14_addon_ssi_source_document_mixin-14.0.1.1.0.dist-info/RECORD
